sd_cloud_utils/__init__.py
sd_cloud_utils/aws/__init__.py
sd_cloud_utils/aws/sqs.py
sd_cloud_utils-0.1.1.dist-info/WHEEL
sd_cloud_utils-0.1.1.dist-info/METADATA
sd_cloud_utils-0.1.1.dist-info/RECORD
