Metadata-Version: 2.1
Name: sd-cloud-utils
Version: 0.1.1
Summary: 
Author: Sean Davis
Author-email: seandavi@gmail.com
Requires-Python: >=3.7,<4.0
Classifier: Programming Language :: Python :: 3
Classifier: Programming Language :: Python :: 3.7
Requires-Dist: boto3 (>=1.9,<2.0)
